modelpy-0.1.3b0.dist-info/METADATA
modelpy-0.1.3b0.dist-info/WHEEL
modelpy-0.1.3b0.dist-info/entry_points.txt
modelpy/__init__.py
modelpy/models.py
modelpy/vehicle.py
modelpy-0.1.3b0.dist-info/RECORD
